{
  "username": "JoeProAI",
  "type": "followers",
  "count": 26,
  "extracted_at": "2025-09-10T17:56:02.583Z",
  "users": [
    "JoeProAI",
    "JoeProAIPassion",
    "twitter",
    "getimg_ai",
    "SunoMusic",
    "capcutapp",
    "Kdenny_astro",
    "krassenstein",
    "momentumdash",
    "gdb",
    "capcutappThe",
    "Kdenny_astroAbs",
    "krassensteinI",
    "momentumdash271",
    "gdbI",
    "lewiswalkerai",
    "NorthstarBrain",
    "elder_plinius",
    "Shadow_Official",
    "cocktailpeanut",
    "JonathanACaruso",
    "TechPalsTalk",
    "elder_pliniusI",
    "aj7secrets",
    "cocktailpeanutN",
    "TechPalsTalkIf"
  ]
}